httpx_ncloud/__init__.py
httpx_ncloud/ncloud_client.py
httpx_ncloud-0.1.0.dist-info/METADATA
httpx_ncloud-0.1.0.dist-info/WHEEL
httpx_ncloud-0.1.0.dist-info/RECORD
